Login_Appl/Login.py
Login_Appl/__init__.py
Login_Appl/login_holder.py
module/Adventure_game.py
module/Age.py
module/Auto_Count.py
module/Calcualtor.py
module/Calendar.py
module/Clock.py
module/Desktop_notifier.py
module/Emoji_Converter.py
module/MobileMoney_Program2.py
module/Number_Guessing1.py
module/Number_Guessing2.py
module/Password_Generator.py
module/RPS1.py
module/Timer.py
module/__init__.py
module/cube.py
module/unicodes.py
module/File/File.py
module/File/__init__.py
module/Login_Appl/Login.py
module/Login_Appl/__init__.py
module/Login_Appl/login_holder.py
module/Word_Guessing/MAIN_Word_Guessing.py
module/Word_Guessing/Word_Guess1.py
module/Word_Guessing/Word_Guess2.py
module/Word_Guessing/__init__.py
module/Word_Guessing/words.py
module/card_creator_2/__init__.py
module/card_creator_2/card_creator.py
module/card_creator_2/utilities.py
module/contact_book/Contact.py
module/contact_book/__init__.py
kmmodule-0.1.dist-info/LICENSE.txt
kmmodule-0.1.dist-info/METADATA
kmmodule-0.1.dist-info/WHEEL
kmmodule-0.1.dist-info/top_level.txt
kmmodule-0.1.dist-info/RECORD
