Metadata-Version: 2.1
Name: kmmodule
Version: 0.1
Summary: Python creations
Author: Kodjo Messie
Author-email: kodjomessie@gmail.com
Classifier: Programming Language :: Python :: 3
Classifier: License :: OSI Approved :: MIT License
License-File: LICENSE.txt
Requires-Dist: requests>=2.25.0
Requires-Dist: plyer>=2.1.0
Requires-Dist: emoji>=2.13.2
